uniprot_redis/__init__.py
uniprot_redis/__main__.py
uniprot_redis/server.py
uniprot_redis/wrapper.py
uniprot_redis/store/__init__.py
uniprot_redis/store/mockup.py
uniprot_redis/store/schemas.py
uniprot_redis-1.8.3.dist-info/METADATA
uniprot_redis-1.8.3.dist-info/WHEEL
uniprot_redis-1.8.3.dist-info/RECORD
