Metadata-Version: 2.4
Name: uniprot-redis
Version: 1.8.3
Summary: Add your description here
Requires-Python: >=3.12
Requires-Dist: docopt>=0.6.2
Requires-Dist: fastapi>=0.115.6
Requires-Dist: pyrediscore>=1.0.3
Requires-Dist: unyprot>=0.1.0
Requires-Dist: uvicorn>=0.34.0
